集成电路设计自动化/集成电路设计与自动化大作业贡献者：23级孟焱昊/modelsim clean/decode47.v
module decode47(a,b,c,d,e,f,g,D3,D2,D1,D0);
  output a,b,c,d,e,f,g;
  input D3,D2,D1,D0;
  reg a,b,c,d,e,f,g;
  always @(D3 or D2 or D1 or D0)
    begin
      case({D3,D2,D1,D0})
        4'd0: {a,b,c,d,e,f,g}=7'b1111110;
        4'd1: {a,b,c,d,e,f,g}=7'b0110000;
        4'd2: {a,b,c,d,e,f,g}=7'b1101101;
        4'd3: {a,b,c,d,e,f,g}=7'b1111001;
        4'd4: {a,b,c,d,e,f,g}=7'b0110011;
        4'd5: {a,b,c,d,e,f,g}=7'b1011011;
        4'd6: {a,b,c,d,e,f,g}=7'b1011111;
        4'd7: {a,b,c,d,e,f,g}=7'b1110000;
        4'd8: {a,b,c,d,e,f,g}=7'b1111111;
        4'd9: {a,b,c,d,e,f,g}=7'b1111011;     
        default: {a,b,c,d,e,f,g}=7'b0;
      endcase
    end
  endmodule

集成电路设计自动化/集成电路设计与自动化大作业贡献者：23级孟焱昊/modelsim/Model jichengzong/decode47_tb.v
`timescale 1ns/1ns

module decode47_tb;
    reg [3:0] input_bcd;
    wire a, b, c, d, e, f, g;
    
    // 实例化被测试模块 - 修正了实例化语法
    decode47 uut(
        .a(a), 
        .b(b), 
        .c(c), 
        .d(d), 
        .e(e), 
        .f(f), 
        .g(g),
        .D3(input_bcd[3]), 
        .D2(input_bcd[2]), 
        .D1(input_bcd[1]), 
        .D0(input_bcd[0])
    );
    
    // 生成测试激励
    initial begin
        $monitor("Time=%0t, BCD=%b, Segments={a=%b, b=%b, c=%b, d=%b, e=%b, f=%b, g=%b}", 
                 $time, input_bcd, a, b, c, d, e, f, g);
        
        // 测试所有可能的输入
        input_bcd = 0;
        repeat(16) begin
            #10 input_bcd = input_bcd + 1;
        end
        
        #10 $finish;
    end
    
    // 生成波形文件
    initial begin
        $dumpfile("decode47_tb.vcd");
        $dumpvars(0, decode47_tb);
    end
    
endmodule

集成电路设计自动化/集成电路设计与自动化大作业贡献者：23级孟焱昊/modelsim/Model jichengzong/decode47_tb.vcd
$date
	Thu Oct 30 20:24:19 2025
$end
$version
	ModelSim Version 10.1c
$end
$timescale
	1ns
$end
$scope module decode47_tb $end
$var reg 4 ! input_bcd [3:0] $end
$var wire 1 " a $end
$var wire 1 # b $end
$var wire 1 $ c $end
$var wire 1 % d $end
$var wire 1 & e $end
$var wire 1 ' f $end
$var wire 1 ( g $end
$scope module uut $end
$var reg 1 ) a $end
$var reg 1 * b $end
$var reg 1 + c $end
$var reg 1 , d $end
$var reg 1 - e $end
$var reg 1 . f $end
$var reg 1 / g $end
$var wire 1 0 D3 $end
$var wire 1 1 D2 $end
$var wire 1 2 D1 $end
$var wire 1 3 D0 $end
$upscope $end
$upscope $end
$enddefinitions $end
#0
$dumpvars
b0 !
1)
1*
1+
1,
1-
1.
0/
1"
1#
1$
1%
1&
1'
0(
03
02
01
00
$end
#10
b1 !
13
0.
0-
0,
0)
0'
0&
0%
0"
#20
b10 !
03
12
1/
1-
1,
0+
1)
1(
1&
1%
0$
1"
#30
b11 !
13
0-
1+
0&
1$
#40
b100 !
03
02
11
1.
0,
0)
1'
0%
0"
#50
b101 !
13
1,
0*
1)
1%
0#
1"
#60
b110 !
03
12
1-
1&
#70
b111 !
13
0/
0.
0-
0,
1*
0(
0'
0&
0%
1#
#80
b1000 !
03
02
01
10
1/
1.
1-
1,
1(
1'
1&
1%
#90
b1001 !
13
0-
0&
#100
b1010 !
03
12
0/
0.
0,
0+
0*
0)
0(
0'
0%
0$
0#
0"
#110
b1011 !
13
#120
b1100 !
03
02
11
#130
b1101 !
13
#140
b1110 !
03
12
#150
b1111 !
13
#160
b0 !
03
02
01
00
1.
1-
1,
1+
1*
1)
1'
1&
1%
1$
1#
1"
