集成电路设计自动化/集成电路设计与自动化大作业贡献者：23级孟焱昊/modelsim clean/decoder3to8 .v
`timescale 1ns/1ps
module decoder3to8 (
    input  wire       en,
    input  wire [2:0] in,
    output reg  [7:0] out
);

always @(*) begin
    if (!en)
        out = 8'b1111_1111;
    else begin
        case (in)
            3'd0: out = 8'b1111_1110;
            3'd1: out = 8'b1111_1101;
            3'd2: out = 8'b1111_1011;
            3'd3: out = 8'b1111_0111;
            3'd4: out = 8'b1110_1111;
            3'd5: out = 8'b1101_1111;
            3'd6: out = 8'b1011_1111;
            3'd7: out = 8'b0111_1111;
            default: out = 8'b1111_1111;
        endcase
    end
end

endmodule

集成电路设计自动化/集成电路设计与自动化大作业贡献者：23级孟焱昊/38yimaqi/decoder3to8_tb.v
`timescale 1ns/1ps
module decoder3to8_tb;

reg       en;
reg [2:0] in;
wire[7:0] out;

integer i;

decoder3to8 u0 (
    .en(en),
    .in(in),
    .out(out)
);

initial begin
    en = 0; in = 3'b000; #10;
    en = 1;              #10;
    for (i = 0; i < 8; i = i + 1) begin
        in = i; #10;
    end
    en = 0;              #10;
    $display("Simulation Finished");
    $finish;
end

endmodule

集成电路设计自动化/集成电路设计与自动化大作业贡献者：23级孟焱昊/modelsim/Model jichengzong/decoder3to8.vcd
$date
	Sat Dec 20 17:08:45 2025
$end
$version
	ModelSim Version 10.1c
$end
$timescale
	1ps
$end
$scope module decoder3to8_tb $end
$var reg 1 ! en $end
$var reg 3 " in [2:0] $end
$var wire 1 # out [7] $end
$var wire 1 $ out [6] $end
$var wire 1 % out [5] $end
$var wire 1 & out [4] $end
$var wire 1 ' out [3] $end
$var wire 1 ( out [2] $end
$var wire 1 ) out [1] $end
$var wire 1 * out [0] $end
$var integer 32 + i $end
$scope module u0 $end
$var wire 1 , en $end
$var wire 1 - in [2] $end
$var wire 1 . in [1] $end
$var wire 1 / in [0] $end
$var reg 8 0 out [7:0] $end
$upscope $end
$upscope $end
$enddefinitions $end
#0
$dumpvars
0!
b0 "
b11111111 0
bx +
1*
1)
1(
1'
1&
1%
1$
1#
0/
0.
0-
0,
$end
#10000
1!
1,
b11111110 0
0*
#20000
b0 +
#30000
b1 +
b1 "
1/
b11111101 0
1*
0)
#40000
b10 +
b10 "
0/
1.
b11111011 0
1)
0(
#50000
b11 +
b11 "
1/
b11110111 0
1(
0'
#60000
b100 +
b100 "
0/
0.
1-
b11101111 0
1'
0&
#70000
b101 +
b101 "
1/
b11011111 0
1&
0%
#80000
b110 +
b110 "
0/
1.
b10111111 0
1%
0$
#90000
b111 +
b111 "
1/
b1111111 0
1$
0#
#100000
b1000 +
0!
0,
b11111111 0
1#
